emailsys
