Metadata-Version: 1.0
Name: django-emailsys
Version: 0.0.24
Summary: Provide the ability to send emails/sms using WebServices
Home-page: https://bitbucket.org/rsneh/django-emailsys
Author: Ron Sneh
Author-email: me@ronsneh.com
License: UNKNOWN
Platform: UNKNOWN
